flask_breadcrumb/__init__.py
flask_breadcrumb-1.0.10.dist-info/METADATA
flask_breadcrumb-1.0.10.dist-info/WHEEL
flask_breadcrumb-1.0.10.dist-info/licenses/LICENSE
flask_breadcrumb-1.0.10.dist-info/RECORD
