Metadata-Version: 2.4
Name: flask-breadcrumb
Version: 1.0.10
Summary: None
Author-email: Coulton Fraser <cjrfraser@gmail.com>
License-File: LICENSE
Requires-Python: >=3.10
Requires-Dist: flask>=3.0.0
